{
  "hash": "cb68eb1b32283f29e0621dc3fe83a2e2",
  "result": {
    "engine": "knitr",
    "markdown": "---\ntitle: \"PA 8: Hot Ones\"\nsubtitle: \"Data Joins\"\nformat: \n  html:\n    code-tools: true\n    toc: true\neditor: source\nexecute: \n  error: true\n  echo: true\n  message: false\n  warning: false\n---\n\n\n::: {.cell}\n\n```{.r .cell-code}\n# load packages\nlibrary(readxl) \nlibrary(tidyverse)\n```\n:::\n\n\n\n\n\n::: {.cell}\n\n```{.r .cell-code}\nepisodes <- read_csv('https://raw.githubusercontent.com/rfordatascience/tidytuesday/main/data/2023/2023-08-08/episodes.csv')\nsauces <- read_csv('https://raw.githubusercontent.com/rfordatascience/tidytuesday/main/data/2023/2023-08-08/sauces.csv')\nseasons <- read_csv('https://raw.githubusercontent.com/rfordatascience/tidytuesday/main/data/2023/2023-08-08/seasons.csv')\n```\n:::\n\n\n\n\n::: {.cell}\n\n```{.r .cell-code}\ncities <- read_csv('https://raw.githubusercontent.com/rfordatascience/tidytuesday/main/data/2026/2026-05-12/cities.csv')\nlinks <- read_csv('https://raw.githubusercontent.com/rfordatascience/tidytuesday/main/data/2026/2026-05-12/links.csv')\n```\n:::\n\n\n::: {.cell}\n\n```{.r .cell-code}\nlinked_cities <- links |> \n  left_join(cities, join_by(source == id)) |> \n  rename_with(.fn = \\(x) paste0(\"source_\", x), \n              .cols = name:continent) |> \n  left_join(cities, join_by(target == id))\n```\n:::\n\n\n\n::: {.cell}\n\n```{.r .cell-code}\nlinked_cities |> \n  filter(is.na(source_name) | is.na(name))\n```\n\n::: {.cell-output .cell-output-stdout}\n\n```\n# A tibble: 0 × 14\n# ℹ 14 variables: source <chr>, target <chr>, source_name <chr>,\n#   source_lng <dbl>, source_lat <dbl>, source_country <chr>,\n#   source_countrycd <chr>, source_continent <chr>, name <chr>, lng <dbl>,\n#   lat <dbl>, country <chr>, countrycd <chr>, continent <chr>\n```\n\n\n:::\n:::\n\n\n\nHow many cities are not linked to a sister city?\n\n\n::: {.cell}\n\n```{.r .cell-code}\ncities |> \n  anti_join(linked_cities,\n            by = join_by(id == source))\n```\n\n::: {.cell-output .cell-output-stdout}\n\n```\n# A tibble: 1,598 × 7\n   id      name               lng   lat country countrycd continent\n   <chr>   <chr>            <dbl> <dbl> <chr>   <chr>     <chr>    \n 1 Q385684 Ono               136.  36.0 Japan   JP        Asia     \n 2 Q386052 Ōshū              141.  39.1 Japan   JP        Asia     \n 3 Q428989 Noboribetsu       141.  42.4 Japan   JP        Asia     \n 4 Q495809 Fujimi            140.  35.9 Japan   JP        Asia     \n 5 Q496472 Kuwana            137.  35.1 Japan   JP        Asia     \n 6 Q502205 Nemuro            146.  43.3 Japan   JP        Asia     \n 7 Q596486 Fujioka           139.  36.3 Japan   JP        Asia     \n 8 Q622594 Takayama          137.  36.1 Japan   JP        Asia     \n 9 Q642018 Natori            141.  38.2 Japan   JP        Asia     \n10 Q653372 Higashihiroshima  133.  34.4 Japan   JP        Asia     \n# ℹ 1,588 more rows\n```\n\n\n:::\n:::\n\n\n",
    "supporting": [],
    "filters": [
      "rmarkdown/pagebreak.lua"
    ],
    "includes": {},
    "engineDependencies": {},
    "preserve": {},
    "postProcess": true
  }
}